{
  "Address": "Адрес",
  "Amount": "Сумма",
  "Balance": "Баланс",
  "ClientIdentifier": "Идентификатор клиента",
  "Commission": "Комиссия",
  "CreationTime": "Время создания",
  "Description": "Назначение",
  "ExpirationPeriod": "Срок действия",
  "Id": "ID",
  "Identifier": "Идентификатор",
  "IncomeAmount": "Приход",
  "InvoiceId": "ID счета",
  "OrderId": "ID заказа",
  "OutcomeAmount": "Расход",
  "PartnerIdentifier": "WMID корреспондента",
  "PrimaryId": "Первичный ID системы",
  "ProtectionPeriod": "Срок протекции",
  "SecondaryId": "Вторичный ID системы",
  "SourcePurse": "Откуда",
  "State": "Состояние",
  "TargetIdentifier": "Идентификатор получателя",
  "TargetPurse": "Куда",
  "TransferBundleId": "ID перевода пакета",
  "TransferId": "ID перевода",
  "TransferPrimaryId": "Первичный ID перевода",
  "Type": "Тип",
  "UpdateTime": "Обновлено",
  "СreationTime": "Создано"
}